stream_sqlite.py
stream_sqlite-0.0.41.dist-info/LICENSE
stream_sqlite-0.0.41.dist-info/METADATA
stream_sqlite-0.0.41.dist-info/WHEEL
stream_sqlite-0.0.41.dist-info/top_level.txt
stream_sqlite-0.0.41.dist-info/RECORD
