Metadata-Version: 2.1
Name: stream-sqlite
Version: 0.0.41
Summary: Python function to extract all the rows from a SQLite database file concurrently with iterating over its bytes, without needing random access to the file
Home-page: https://github.com/uktrade/stream-sqlite
Author: Department for International Trade
Author-email: sre@digital.trade.gov.uk
Classifier: Programming Language :: Python :: 3
Classifier: License :: OSI Approved :: MIT License
Classifier: Topic :: Database
Requires-Python: >=3.5.0
License-File: LICENSE
